setup.py
algotemplate/__init__.py
pumptemplate.egg-info/PKG-INFO
pumptemplate.egg-info/SOURCES.txt
pumptemplate.egg-info/dependency_links.txt
pumptemplate.egg-info/not-zip-safe
pumptemplate.egg-info/top_level.txt