Metadata-Version: 2.1
Name: pumptemplate
Version: 0.3
Summary: The funniest joke in the world
Home-page: http://github.com/dhanapalschandran/algotemplate
Author: Dhanapal Chandran
Author-email: dhanapal@gmail.com
License: MIT
Platform: UNKNOWN
